{"frames":[{"filename":"sprite_1","frame":{"x":0,"y":0,"w":128,"h":128},"rotated":false,"trimmed":false,"spriteSourceSize":{"x":0,"y":0,"w":128,"h":128},"sourceSize":{"w":128,"h":128}},{"filename":"sprite_2","frame":{"x":0,"y":129,"w":128,"h":128},"rotated":false,"trimmed":false,"spriteSourceSize":{"x":0,"y":0,"w":128,"h":128},"sourceSize":{"w":128,"h":128}},{"filename":"sprite_3","frame":{"x":129,"y":0,"w":128,"h":128},"rotated":false,"trimmed":false,"spriteSourceSize":{"x":0,"y":0,"w":128,"h":128},"sourceSize":{"w":128,"h":128}},{"filename":"sprite_4","frame":{"x":129,"y":129,"w":128,"h":128},"rotated":false,"trimmed":false,"spriteSourceSize":{"x":0,"y":0,"w":128,"h":128},"sourceSize":{"w":128,"h":128}},{"filename":"sprite_5","frame":{"x":0,"y":258,"w":128,"h":128},"rotated":false,"trimmed":false,"spriteSourceSize":{"x":0,"y":0,"w":128,"h":128},"sourceSize":{"w":128,"h":128}},{"filename":"sprite_6","frame":{"x":129,"y":258,"w":128,"h":128},"rotated":false,"trimmed":false,"spriteSourceSize":{"x":0,"y":0,"w":128,"h":128},"sourceSize":{"w":128,"h":128}},{"filename":"sprite_7","frame":{"x":258,"y":0,"w":128,"h":128},"rotated":false,"trimmed":false,"spriteSourceSize":{"x":0,"y":0,"w":128,"h":128},"sourceSize":{"w":128,"h":128}},{"filename":"sprite_8","frame":{"x":258,"y":129,"w":128,"h":128},"rotated":false,"trimmed":false,"spriteSourceSize":{"x":0,"y":0,"w":128,"h":128},"sourceSize":{"w":128,"h":128}}],"meta":{"app":"https://www.leshylabs.com/apps/sstool/","version":"Leshy SpriteSheet Tool v0.8.4","image":"asteroid_sheet.png","size":{"w":386,"h":386},"scale":1}}